morpheus/__init__.py
morpheus/api/__init__py
morpheus/api/defaults.py
morpheus/api/interfaces.py
morpheus/classification/__init__.py
morpheus/classification/classifier.py
morpheus/classification/threshold.py
morpheus/classification/train.py
morpheus/confidence/__init__.py
morpheus/confidence/trustscore.py
morpheus/configuration/Types.py
morpheus/configuration/__init__.py
morpheus/counterfactual/__init__.py
morpheus/counterfactual/cf.py
morpheus/counterfactual/generate.py
morpheus/datasets/__init__.py
morpheus/datasets/spatial_dataset.py
morpheus/datasets/torch_dataset.py
morpheus/utils/__init__.py
morpheus/utils/gradients.py
morpheus/utils/patchify.py
morpheus/utils/saving.py
morpheus/utils/version.py
morpheus_spatial-1.1.0.dist-info/METADATA
morpheus_spatial-1.1.0.dist-info/WHEEL
morpheus_spatial-1.1.0.dist-info/RECORD
