Metadata-Version: 2.3
Name: morpheus-spatial
Version: 1.1.0
Summary: 
Author: neonine2
Author-email: jerry.wang95@yahoo.ca
Requires-Python: >=3.9,<3.12
Classifier: Programming Language :: Python :: 3
Classifier: Programming Language :: Python :: 3.9
Classifier: Programming Language :: Python :: 3.10
Classifier: Programming Language :: Python :: 3.11
Provides-Extra: audio
Requires-Dist: Jinja2 (>=3.1.4)
Requires-Dist: aiohttp (>=3.9.4)
Requires-Dist: certifi (>=2024.7.4)
Requires-Dist: dill (>=0.3.8,<0.4.0)
Requires-Dist: h5py (>=3.10.0,<4.0.0)
Requires-Dist: idna (>=3.7)
Requires-Dist: lightning (>=2.0.0,<3.0.0)
Requires-Dist: numpy (<=1.26)
Requires-Dist: pandas (==2.2.1)
Requires-Dist: pillow (>=10.3.0)
Requires-Dist: psutil (>=7.0.0,<8.0.0)
Requires-Dist: ray (>=2.11.0,<3.0.0)
Requires-Dist: scikit-learn (>=1.5.0)
Requires-Dist: torch (==2.0.0)
Requires-Dist: torchvision (>=0.15.1,<0.16.0)
